tikkie2/__init__.py
tikkie2/_session.py
tikkie2/_util.py
tikkie2/_version.py
tikkie2/errors.py
tikkie2/py.typed
tikkie2/utils.py
tikkie2/v2/__init__.py
tikkie2/v2/ideal_qr.py
tikkie2/v2/ideal_qr_notification.py
tikkie2/v2/models.py
tikkie2/v2/payment.py
tikkie2/v2/payment_request.py
tikkie2/v2/payment_request_notification.py
tikkie2/v2/refund.py
tikkie2/v2/sandbox_app.py
tikkie2/v2/transaction_bundle.py
tikkie2/v2/transactions_notifications.py
tikkie_api-2.0.0.dist-info/LICENSE
tikkie_api-2.0.0.dist-info/METADATA
tikkie_api-2.0.0.dist-info/WHEEL
tikkie_api-2.0.0.dist-info/top_level.txt
tikkie_api-2.0.0.dist-info/RECORD
